alchemy/__init__.py
alchemy/__version__.py
alchemy/example.py
alchemy/logger.py
alchemy_catalyst-20.3.dist-info/LICENSE
alchemy_catalyst-20.3.dist-info/METADATA
alchemy_catalyst-20.3.dist-info/WHEEL
alchemy_catalyst-20.3.dist-info/top_level.txt
alchemy_catalyst-20.3.dist-info/RECORD
