Metadata-Version: 2.1
Name: alchemy-catalyst
Version: 20.3
Summary: Alchemy. Experiments logging & visualization.
Home-page: https://github.com/catalyst-team/alchemy
Author: David Kuryakin
Author-email: dkuryakin@gmail.com
License: Apache License 2.0
Download-URL: https://github.com/catalyst-team/alchemy
Project-URL: Bug Tracker, https://github.com/catalyst-team/alchemy/issues
Project-URL: Documentation, https://catalyst-team.github.io/alchemy
Project-URL: Source Code, https://github.com/catalyst-team/alchemy
Keywords: Machine Learning,Deep Learning,PyTorch
Platform: UNKNOWN
Classifier: Environment :: Console
Classifier: Natural Language :: English
Classifier: Development Status :: 4 - Beta
Classifier: Operating System :: OS Independent
Classifier: License :: OSI Approved :: Apache Software License
Classifier: Intended Audience :: Developers
Classifier: Intended Audience :: Science/Research
Classifier: Topic :: Scientific/Engineering :: Artificial Intelligence
Classifier: Topic :: Scientific/Engineering :: Information Analysis
Classifier: Topic :: System :: Logging
Classifier: Topic :: System :: Monitoring
Classifier: Programming Language :: Python
Classifier: Programming Language :: Python :: 3.6
Classifier: Programming Language :: Python :: 3.7
Classifier: Programming Language :: Python :: Implementation :: CPython
Requires-Python: >=3.5.0
Requires-Dist: requests (==2.22.0)
